CHANGES
LICENSE
MANIFEST.in
README.rst
setup.py
typeargs.py
typeargs.egg-info/PKG-INFO
typeargs.egg-info/SOURCES.txt
typeargs.egg-info/dependency_links.txt
typeargs.egg-info/top_level.txt